sktime_dl/__init__.py
sktime_dl/classifiers/__init__.py
sktime_dl/classifiers/deeplearning/__init__.py
sktime_dl/classifiers/deeplearning/_base.py
sktime_dl/classifiers/deeplearning/_cnn.py
sktime_dl/classifiers/deeplearning/_encoder.py
sktime_dl/classifiers/deeplearning/_fcn.py
sktime_dl/classifiers/deeplearning/_mcdcnn.py
sktime_dl/classifiers/deeplearning/_mcnn.py
sktime_dl/classifiers/deeplearning/_mlp.py
sktime_dl/classifiers/deeplearning/_resnet.py
sktime_dl/classifiers/deeplearning/_tlenet.py
sktime_dl/classifiers/deeplearning/_tuned_cnn.py
sktime_dl/classifiers/deeplearning/_twiesn.py
sktime_dl/classifiers/deeplearning/tests/__init__.py
sktime_dl/classifiers/deeplearning/tests/test_dl4tscnetworks.py
sktime_dl-0.1.0.dist-info/LICENSE
sktime_dl-0.1.0.dist-info/METADATA
sktime_dl-0.1.0.dist-info/WHEEL
sktime_dl-0.1.0.dist-info/top_level.txt
sktime_dl-0.1.0.dist-info/RECORD
