Metadata-Version: 2.1
Name: sktime-dl
Version: 0.1.0
Summary: Deep learning extension package for sktime, a scikit-learn compatible toolbox for learning with time series data
Home-page: https://github.com/uea-machine-learning/sktime-dl
Maintainer: F. Király
Maintainer-email: fkiraly@turing.ac.uk
License: BSD-3-Clause
Download-URL: https://pypi.org/project/sktime-dl/#files
Platform: UNKNOWN
Classifier: Intended Audience :: Science/Research
Classifier: Intended Audience :: Developers
Classifier: License :: OSI Approved
Classifier: Programming Language :: Python
Classifier: Topic :: Software Development
Classifier: Topic :: Scientific/Engineering
Classifier: Operating System :: Microsoft :: Windows
Classifier: Operating System :: POSIX
Classifier: Operating System :: Unix
Classifier: Operating System :: MacOS
Classifier: Programming Language :: Python :: 3.6
Provides-Extra: tests
Provides-Extra: docs
